README.md
setup.cfg
setup.py
ezstr/__init__.py
ezstr.egg-info/PKG-INFO
ezstr.egg-info/SOURCES.txt
ezstr.egg-info/dependency_links.txt
ezstr.egg-info/not-zip-safe
ezstr.egg-info/top_level.txt