Metadata-Version: 2.1
Name: ezstr
Version: 0.2
Summary: No more tostring boilerplate
Home-page: https://github.com/MichaelVerdegaal/ezstr/archive/0.2.tar.gz
Author: Michael Verdegaal
Author-email: michaelverdegaal@hotmail.nl
License: MIT
Platform: UNKNOWN
